ruqia-0.0.23.data/data/my_data/data_file
ruqiya/__init__.py
ruqiya/package_data.dat
ruqiya/replace_words_dict.py
ruqiya/ruqiya.py
ruqiya/stopwords.py
ruqia-0.0.23.dist-info/METADATA
ruqia-0.0.23.dist-info/WHEEL
ruqia-0.0.23.dist-info/entry_points.txt
ruqia-0.0.23.dist-info/top_level.txt
ruqia-0.0.23.dist-info/RECORD
