Metadata-Version: 2.1
Name: ruqia
Version: 0.0.23
Summary: Arabic NLP
Home-page: https://github.com/Ruqyai/Ruqia-Library
Author: Ruqiya Bin Safi
Author-email: 
Project-URL: Bug Reports, https://github.com/Ruqyai/Ruqia-Library/issues
Project-URL: Become a sponsor, https://github.com/sponsors/Ruqyai
Project-URL: Source, https://github.com/Ruqyai/Ruqia-Library
Keywords: Arabic,NLP,development
Classifier: Development Status :: 3 - Alpha
Classifier: Intended Audience :: Developers
Classifier: Topic :: Software Development :: Build Tools
Classifier: License :: OSI Approved :: MIT License
Classifier: Programming Language :: Python :: 3
Classifier: Programming Language :: Python :: 3.7
Classifier: Programming Language :: Python :: 3.8
Classifier: Programming Language :: Python :: 3.9
Classifier: Programming Language :: Python :: 3.10
Classifier: Programming Language :: Python :: 3.11
Classifier: Programming Language :: Python :: 3 :: Only
Requires-Python: >=3.7, <4
Requires-Dist: peppercorn
Provides-Extra: dev
Requires-Dist: check-manifest ; extra == 'dev'
Provides-Extra: test
Requires-Dist: coverage ; extra == 'test'
